datauri/__init__.py
datauri/datauri.py
datauri-1.0.0.dist-info/DESCRIPTION.rst
datauri-1.0.0.dist-info/METADATA
datauri-1.0.0.dist-info/RECORD
datauri-1.0.0.dist-info/WHEEL
datauri-1.0.0.dist-info/metadata.json
datauri-1.0.0.dist-info/top_level.txt
