Metadata-Version: 2.0
Name: datauri
Version: 1.0.0
Summary: implementation of the data uri scheme defined in rfc2397
Home-page: https://github.com/eclecticiq/python-data-uri
Author: EclecticIQ
Author-email: engineering@eclecticiq.com
License: BSD
Platform: UNKNOWN
Classifier: Development Status :: 4 - Beta
Classifier: License :: OSI Approved :: BSD License
Classifier: Operating System :: OS Independent
Classifier: Programming Language :: Python
Classifier: Programming Language :: Python :: 3
